<?xml version="1.0" encoding="UTF-8"?>

<beans xmlns="http://www.springframework.org/schema/beans"
    xmlns:xsi="http://www.w3.org/2001/XMLSchema-instance"
    xsi:schemaLocation="http://www.springframework.org/schema/beans
        https://www.springframework.org/schema/beans/spring-beans.xsd">


<!-- How to inject a Collection inside a bean -->
<!-- Configuring list of beans / points to inject to the point property of Triangle which is Collection of type Point -->        
<bean id="point1" class="com.B8CollectionInjection.Point">
	<property name="x" value="0"></property>
	<property name="y" value="0"></property>
</bean>

<bean id="point2" class="com.B8CollectionInjection.Point">
	<property name="x" value="-20"></property>
	<property name="y" value="0"></property>
</bean>

<bean id="point3" class="com.B8CollectionInjection.Point">
	<property name="x" value="20"></property>
	<property name="y" value="0"></property>
</bean>
        
        
<!-- Bean for Triangle class -->
<bean id= "triangle" class="com.B8CollectionInjection.Triangle">
	<property name="points">
		<list>
			<ref bean="point1"/>
			<ref bean="point2"/>
			<ref bean="point3"/>
		</list>
	</property>
</bean>






</beans>